Metadata-Version: 1.0
Name: dilligafDistribution
Version: 2.0
Summary: Gaussian and Binomial distributions
Home-page: UNKNOWN
Author: Sara Estes
Author-email: saraestes22314@gmail.com
License: UNKNOWN
Platform: UNKNOWN
